kraken/__init__.py
kraken/_version.py
kraken/cli.py
kraken/base_api/__init__.py
kraken/exceptions/__init__.py
kraken/futures/__init__.py
kraken/futures/funding.py
kraken/futures/market.py
kraken/futures/trade.py
kraken/futures/user.py
kraken/futures/ws_client.py
kraken/futures/websocket/__init__.py
kraken/spot/__init__.py
kraken/spot/earn.py
kraken/spot/funding.py
kraken/spot/market.py
kraken/spot/orderbook.py
kraken/spot/trade.py
kraken/spot/user.py
kraken/spot/ws_client.py
kraken/spot/websocket/__init__.py
kraken/spot/websocket/connectors.py
kraken/utils/__init__.py
kraken/utils/utils.py
python_kraken_sdk-3.2.6.dist-info/licenses/LICENSE
python_kraken_sdk-3.2.6.dist-info/METADATA
python_kraken_sdk-3.2.6.dist-info/WHEEL
python_kraken_sdk-3.2.6.dist-info/entry_points.txt
python_kraken_sdk-3.2.6.dist-info/top_level.txt
python_kraken_sdk-3.2.6.dist-info/RECORD
