Metadata-Version: 2.4
Name: python-kraken-sdk
Version: 3.2.6
Summary: Command-line tool and collection of REST and websocket clients to interact with the Kraken Crypto Asset Exchange.
Author-email: Benjamin Thomas Schwertfeger <contact@b-schwertfeger.de>
Maintainer-email: Benjamin Thomas Schwertfeger <contact@b-schwertfeger.de>
License-Expression: Apache-2.0
Project-URL: Homepage, https://github.com/btschwertfeger/python-kraken-sdk
Project-URL: Documentation, https://python-kraken-sdk.readthedocs.io/en/stable/
Project-URL: Changelog, https://github.com/btschwertfeger/python-kraken-sdk/releases
Project-URL: Bug Tracker, https://github.com/btschwertfeger/python-kraken-sdk/issues
Keywords: crypto,trading,kraken,exchange,api,sdk,kraken crypto asset exchange,automation
Classifier: Development Status :: 5 - Production/Stable
Classifier: Framework :: AsyncIO
Classifier: Intended Audience :: Developers
Classifier: Natural Language :: English
Classifier: Operating System :: MacOS
Classifier: Operating System :: Unix
Classifier: Programming Language :: Python :: 3.11
Classifier: Programming Language :: Python :: 3.12
Classifier: Programming Language :: Python :: 3.13
Classifier: Programming Language :: Python
Classifier: Topic :: Internet :: WWW/HTTP
Classifier: Topic :: Office/Business :: Financial :: Investment
Classifier: Topic :: Office/Business :: Financial
Classifier: Topic :: Software Development :: Libraries :: Python Modules
Classifier: Topic :: Utilities
Requires-Python: >=3.11
License-File: LICENSE
Requires-Dist: requests
Requires-Dist: websockets>=14.1
Requires-Dist: click
Requires-Dist: cloup
Requires-Dist: orjson
Requires-Dist: aiohttp
Dynamic: license-file
